[
  {
    "waktu": "2025-07-08T13:37:11.368043",
    "modal_awal": 3233593,
    "total_pemasukan": 312451,
    "total_pengeluaran": 339486552,
    "rugi": 339174101,
    "profit": 0
  },
  {
    "waktu": "2025-07-08T13:38:11.368043",
    "modal_awal": 699172,
    "total_pemasukan": 218273,
    "total_pengeluaran": 392471479,
    "rugi": 392253206,
    "profit": 0
  },
  {
    "waktu": "2025-07-08T13:39:11.368043",
    "modal_awal": 4252122,
    "total_pemasukan": 557546,
    "total_pengeluaran": 278288732,
    "rugi": 277731186,
    "profit": 0
  },
  {
    "waktu": "2025-07-08T13:40:11.368043",
    "modal_awal": 3677879,
    "total_pemasukan": 397424,
    "total_pengeluaran": 172691985,
    "rugi": 172294561,
    "profit": 0
  },
  {
    "waktu": "2025-07-08T13:41:11.368043",
    "modal_awal": 3128296,
    "total_pemasukan": 572172,
    "total_pengeluaran": 166622311,
    "rugi": 166050139,
    "profit": 0
  },
  {
    "waktu": "2025-07-08T13:42:11.368043",
    "modal_awal": 2681732,
    "total_pemasukan": 987130,
    "total_pengeluaran": 410077831,
    "rugi": 409090701,
    "profit": 0
  },
  {
    "waktu": "2025-07-08T13:43:11.368043",
    "modal_awal": 3440215,
    "total_pemasukan": 509013,
    "total_pengeluaran": 368375801,
    "rugi": 367866788,
    "profit": 0
  },
  {
    "waktu": "2025-07-08T13:44:11.368043",
    "modal_awal": 4301158,
    "total_pemasukan": 268324,
    "total_pengeluaran": 272298137,
    "rugi": 272029813,
    "profit": 0
  },
  {
    "waktu": "2025-07-08T13:45:11.368043",
    "modal_awal": 4370461,
    "total_pemasukan": 221564,
    "total_pengeluaran": 411251929,
    "rugi": 411030365,
    "profit": 0
  },
  {
    "waktu": "2025-07-08T13:46:11.368043",
    "modal_awal": 2189446,
    "total_pemasukan": 899076,
    "total_pengeluaran": 221441634,
    "rugi": 220542558,
    "profit": 0
  },
  {
    "waktu": "2025-07-08T13:47:11.368043",
    "modal_awal": 1723472,
    "total_pemasukan": 269220,
    "total_pengeluaran": 142963802,
    "rugi": 142694582,
    "profit": 0
  },
  {
    "waktu": "2025-07-08T13:48:11.368043",
    "modal_awal": 2145272,
    "total_pemasukan": 257102,
    "total_pengeluaran": 275468584,
    "rugi": 275211482,
    "profit": 0
  },
  {
    "waktu": "2025-07-08T13:49:11.368043",
    "modal_awal": 1341694,
    "total_pemasukan": 386437,
    "total_pengeluaran": 230737432,
    "rugi": 230350995,
    "profit": 0
  },
  {
    "waktu": "2025-07-08T13:50:11.368043",
    "modal_awal": 2664195,
    "total_pemasukan": 467913,
    "total_pengeluaran": 379652134,
    "rugi": 379184221,
    "profit": 0
  },
  {
    "waktu": "2025-07-08T13:51:11.368043",
    "modal_awal": 4383650,
    "total_pemasukan": 635807,
    "total_pengeluaran": 106107778,
    "rugi": 105471971,
    "profit": 0
  },
  {
    "waktu": "2025-07-08T13:52:11.368043",
    "modal_awal": 1452950,
    "total_pemasukan": 987041,
    "total_pengeluaran": 419162662,
    "rugi": 418175621,
    "profit": 0
  },
  {
    "waktu": "2025-07-08T13:53:11.368043",
    "modal_awal": 4784539,
    "total_pemasukan": 760438,
    "total_pengeluaran": 309104845,
    "rugi": 308344407,
    "profit": 0
  },
  {
    "waktu": "2025-07-08T13:54:11.368043",
    "modal_awal": 3220763,
    "total_pemasukan": 414558,
    "total_pengeluaran": 276966167,
    "rugi": 276551609,
    "profit": 0
  },
  {
    "waktu": "2025-07-08T13:55:11.368043",
    "modal_awal": 4464536,
    "total_pemasukan": 130207,
    "total_pengeluaran": 333174918,
    "rugi": 333044711,
    "profit": 0
  },
  {
    "waktu": "2025-07-08T13:56:11.368043",
    "modal_awal": 4580868,
    "total_pemasukan": 210330,
    "total_pengeluaran": 482458701,
    "rugi": 482248371,
    "profit": 0
  },
  {
    "waktu": "2025-07-08T13:57:11.368043",
    "modal_awal": 1001860,
    "total_pemasukan": 862972,
    "total_pengeluaran": 380644606,
    "rugi": 379781634,
    "profit": 0
  },
  {
    "waktu": "2025-07-08T13:58:11.368043",
    "modal_awal": 1503425,
    "total_pemasukan": 117689,
    "total_pengeluaran": 234307389,
    "rugi": 234189700,
    "profit": 0
  },
  {
    "waktu": "2025-07-08T13:59:11.368043",
    "modal_awal": 1062902,
    "total_pemasukan": 279760,
    "total_pengeluaran": 409870686,
    "rugi": 409590926,
    "profit": 0
  },
  {
    "waktu": "2025-07-08T14:00:11.368043",
    "modal_awal": 4441168,
    "total_pemasukan": 309370,
    "total_pengeluaran": 241202418,
    "rugi": 240893048,
    "profit": 0
  },
  {
    "waktu": "2025-07-08T14:01:11.368043",
    "modal_awal": 523365,
    "total_pemasukan": 989714,
    "total_pengeluaran": 207595614,
    "rugi": 206605900,
    "profit": 0
  },
  {
    "waktu": "2025-07-08T14:02:11.368043",
    "modal_awal": 3132339,
    "total_pemasukan": 801511,
    "total_pengeluaran": 222583265,
    "rugi": 221781754,
    "profit": 0
  },
  {
    "waktu": "2025-07-08T14:03:11.368043",
    "modal_awal": 4527542,
    "total_pemasukan": 917719,
    "total_pengeluaran": 271027843,
    "rugi": 270110124,
    "profit": 0
  },
  {
    "waktu": "2025-07-08T14:04:11.368043",
    "modal_awal": 1246087,
    "total_pemasukan": 577485,
    "total_pengeluaran": 399693100,
    "rugi": 399115615,
    "profit": 0
  },
  {
    "waktu": "2025-07-08T14:05:11.368043",
    "modal_awal": 3849101,
    "total_pemasukan": 900396,
    "total_pengeluaran": 188116949,
    "rugi": 187216553,
    "profit": 0
  },
  {
    "waktu": "2025-07-08T14:06:11.368043",
    "modal_awal": 2634191,
    "total_pemasukan": 880884,
    "total_pengeluaran": 349288458,
    "rugi": 348407574,
    "profit": 0
  },
  {
    "waktu": "2025-07-08T14:07:11.368043",
    "modal_awal": 4203790,
    "total_pemasukan": 962726,
    "total_pengeluaran": 203448144,
    "rugi": 202485418,
    "profit": 0
  },
  {
    "waktu": "2025-07-08T14:08:11.368043",
    "modal_awal": 4846590,
    "total_pemasukan": 792121,
    "total_pengeluaran": 138623439,
    "rugi": 137831318,
    "profit": 0
  },
  {
    "waktu": "2025-07-08T14:09:11.368043",
    "modal_awal": 3559697,
    "total_pemasukan": 803961,
    "total_pengeluaran": 104126709,
    "rugi": 103322748,
    "profit": 0
  },
  {
    "waktu": "2025-07-08T14:10:11.368043",
    "modal_awal": 3928701,
    "total_pemasukan": 551366,
    "total_pengeluaran": 411849469,
    "rugi": 411298103,
    "profit": 0
  },
  {
    "waktu": "2025-07-08T14:11:11.368043",
    "modal_awal": 2301773,
    "total_pemasukan": 691424,
    "total_pengeluaran": 390498963,
    "rugi": 389807539,
    "profit": 0
  },
  {
    "waktu": "2025-07-08T14:12:11.368043",
    "modal_awal": 2893917,
    "total_pemasukan": 330821,
    "total_pengeluaran": 189458492,
    "rugi": 189127671,
    "profit": 0
  },
  {
    "waktu": "2025-07-08T14:13:11.368043",
    "modal_awal": 3044978,
    "total_pemasukan": 444057,
    "total_pengeluaran": 194884142,
    "rugi": 194440085,
    "profit": 0
  },
  {
    "waktu": "2025-07-08T14:14:11.368043",
    "modal_awal": 1805960,
    "total_pemasukan": 221023,
    "total_pengeluaran": 296370122,
    "rugi": 296149099,
    "profit": 0
  },
  {
    "waktu": "2025-07-08T14:15:11.368043",
    "modal_awal": 4574479,
    "total_pemasukan": 765859,
    "total_pengeluaran": 353557963,
    "rugi": 352792104,
    "profit": 0
  },
  {
    "waktu": "2025-07-08T14:16:11.368043",
    "modal_awal": 4942602,
    "total_pemasukan": 146797,
    "total_pengeluaran": 453068160,
    "rugi": 452921363,
    "profit": 0
  },
  {
    "waktu": "2025-07-08T14:17:11.368043",
    "modal_awal": 3214312,
    "total_pemasukan": 362486,
    "total_pengeluaran": 226245246,
    "rugi": 225882760,
    "profit": 0
  },
  {
    "waktu": "2025-07-08T14:18:11.368043",
    "modal_awal": 2847221,
    "total_pemasukan": 577807,
    "total_pengeluaran": 369622988,
    "rugi": 369045181,
    "profit": 0
  },
  {
    "waktu": "2025-07-08T14:19:11.368043",
    "modal_awal": 724074,
    "total_pemasukan": 256113,
    "total_pengeluaran": 151708019,
    "rugi": 151451906,
    "profit": 0
  },
  {
    "waktu": "2025-07-08T14:20:11.368043",
    "modal_awal": 3243147,
    "total_pemasukan": 756623,
    "total_pengeluaran": 447107564,
    "rugi": 446350941,
    "profit": 0
  },
  {
    "waktu": "2025-07-08T14:21:11.368043",
    "modal_awal": 2760402,
    "total_pemasukan": 881809,
    "total_pengeluaran": 387201780,
    "rugi": 386319971,
    "profit": 0
  },
  {
    "waktu": "2025-07-08T14:22:11.368043",
    "modal_awal": 4026565,
    "total_pemasukan": 977977,
    "total_pengeluaran": 143407176,
    "rugi": 142429199,
    "profit": 0
  },
  {
    "waktu": "2025-07-08T14:23:11.368043",
    "modal_awal": 4196236,
    "total_pemasukan": 419536,
    "total_pengeluaran": 223445631,
    "rugi": 223026095,
    "profit": 0
  },
  {
    "waktu": "2025-07-08T14:24:11.368043",
    "modal_awal": 3467516,
    "total_pemasukan": 657108,
    "total_pengeluaran": 266720385,
    "rugi": 266063277,
    "profit": 0
  },
  {
    "waktu": "2025-07-08T14:25:11.368043",
    "modal_awal": 3158988,
    "total_pemasukan": 911113,
    "total_pengeluaran": 417135974,
    "rugi": 416224861,
    "profit": 0
  },
  {
    "waktu": "2025-07-08T14:26:11.368043",
    "modal_awal": 1773034,
    "total_pemasukan": 295504,
    "total_pengeluaran": 486050804,
    "rugi": 485755300,
    "profit": 0
  }
]