[
  {
    "waktu": "2025-07-08T13:37:11.362003",
    "modal_awal": 1280896,
    "total_pemasukan": 242300152,
    "total_pengeluaran": 326215,
    "rugi": 0,
    "profit": 241973937
  },
  {
    "waktu": "2025-07-08T13:38:11.362003",
    "modal_awal": 4126288,
    "total_pemasukan": 404950774,
    "total_pengeluaran": 697871,
    "rugi": 0,
    "profit": 404252903
  },
  {
    "waktu": "2025-07-08T13:39:11.362003",
    "modal_awal": 1376996,
    "total_pemasukan": 387950120,
    "total_pengeluaran": 705355,
    "rugi": 0,
    "profit": 387244765
  },
  {
    "waktu": "2025-07-08T13:40:11.362003",
    "modal_awal": 565376,
    "total_pemasukan": 351850147,
    "total_pengeluaran": 869032,
    "rugi": 0,
    "profit": 350981115
  },
  {
    "waktu": "2025-07-08T13:41:11.362003",
    "modal_awal": 1784894,
    "total_pemasukan": 186450038,
    "total_pengeluaran": 120905,
    "rugi": 0,
    "profit": 186329133
  },
  {
    "waktu": "2025-07-08T13:42:11.362003",
    "modal_awal": 3600325,
    "total_pemasukan": 443780506,
    "total_pengeluaran": 864068,
    "rugi": 0,
    "profit": 442916438
  },
  {
    "waktu": "2025-07-08T13:43:11.362003",
    "modal_awal": 970535,
    "total_pemasukan": 285620322,
    "total_pengeluaran": 652120,
    "rugi": 0,
    "profit": 284968202
  },
  {
    "waktu": "2025-07-08T13:44:11.362003",
    "modal_awal": 2898094,
    "total_pemasukan": 421769642,
    "total_pengeluaran": 845882,
    "rugi": 0,
    "profit": 420923760
  },
  {
    "waktu": "2025-07-08T13:45:11.362003",
    "modal_awal": 661791,
    "total_pemasukan": 341539506,
    "total_pengeluaran": 814209,
    "rugi": 0,
    "profit": 340725297
  },
  {
    "waktu": "2025-07-08T13:46:11.362003",
    "modal_awal": 2798719,
    "total_pemasukan": 292884614,
    "total_pengeluaran": 165904,
    "rugi": 0,
    "profit": 292718710
  },
  {
    "waktu": "2025-07-08T13:47:11.362003",
    "modal_awal": 3184767,
    "total_pemasukan": 355982814,
    "total_pengeluaran": 924800,
    "rugi": 0,
    "profit": 355058014
  },
  {
    "waktu": "2025-07-08T13:48:11.362003",
    "modal_awal": 2125748,
    "total_pemasukan": 295321600,
    "total_pengeluaran": 499094,
    "rugi": 0,
    "profit": 294822506
  },
  {
    "waktu": "2025-07-08T13:49:11.362003",
    "modal_awal": 3694588,
    "total_pemasukan": 272243791,
    "total_pengeluaran": 223079,
    "rugi": 0,
    "profit": 272020712
  },
  {
    "waktu": "2025-07-08T13:50:11.362003",
    "modal_awal": 3570188,
    "total_pemasukan": 434000779,
    "total_pengeluaran": 263715,
    "rugi": 0,
    "profit": 433737064
  },
  {
    "waktu": "2025-07-08T13:51:11.362003",
    "modal_awal": 2750290,
    "total_pemasukan": 371330252,
    "total_pengeluaran": 968053,
    "rugi": 0,
    "profit": 370362199
  },
  {
    "waktu": "2025-07-08T13:52:11.362003",
    "modal_awal": 2339141,
    "total_pemasukan": 397917860,
    "total_pengeluaran": 301903,
    "rugi": 0,
    "profit": 397615957
  },
  {
    "waktu": "2025-07-08T13:53:11.362003",
    "modal_awal": 2863958,
    "total_pemasukan": 469379852,
    "total_pengeluaran": 282562,
    "rugi": 0,
    "profit": 469097290
  },
  {
    "waktu": "2025-07-08T13:54:11.362003",
    "modal_awal": 1556619,
    "total_pemasukan": 427640148,
    "total_pengeluaran": 250002,
    "rugi": 0,
    "profit": 427390146
  },
  {
    "waktu": "2025-07-08T13:55:11.362003",
    "modal_awal": 1434756,
    "total_pemasukan": 459701435,
    "total_pengeluaran": 893218,
    "rugi": 0,
    "profit": 458808217
  },
  {
    "waktu": "2025-07-08T13:56:11.362003",
    "modal_awal": 3976263,
    "total_pemasukan": 221099613,
    "total_pengeluaran": 714953,
    "rugi": 0,
    "profit": 220384660
  },
  {
    "waktu": "2025-07-08T13:57:11.362003",
    "modal_awal": 3324910,
    "total_pemasukan": 217674037,
    "total_pengeluaran": 429950,
    "rugi": 0,
    "profit": 217244087
  },
  {
    "waktu": "2025-07-08T13:58:11.362003",
    "modal_awal": 4711496,
    "total_pemasukan": 152272855,
    "total_pengeluaran": 798581,
    "rugi": 0,
    "profit": 151474274
  },
  {
    "waktu": "2025-07-08T13:59:11.362003",
    "modal_awal": 3593320,
    "total_pemasukan": 218463073,
    "total_pengeluaran": 414213,
    "rugi": 0,
    "profit": 218048860
  },
  {
    "waktu": "2025-07-08T14:00:11.362003",
    "modal_awal": 1858551,
    "total_pemasukan": 435333406,
    "total_pengeluaran": 690932,
    "rugi": 0,
    "profit": 434642474
  },
  {
    "waktu": "2025-07-08T14:01:11.362003",
    "modal_awal": 1385841,
    "total_pemasukan": 434530523,
    "total_pengeluaran": 435271,
    "rugi": 0,
    "profit": 434095252
  },
  {
    "waktu": "2025-07-08T14:02:11.362003",
    "modal_awal": 3744995,
    "total_pemasukan": 254388790,
    "total_pengeluaran": 894579,
    "rugi": 0,
    "profit": 253494211
  },
  {
    "waktu": "2025-07-08T14:03:11.362003",
    "modal_awal": 3646369,
    "total_pemasukan": 339489401,
    "total_pengeluaran": 616529,
    "rugi": 0,
    "profit": 338872872
  },
  {
    "waktu": "2025-07-08T14:04:11.362003",
    "modal_awal": 4537571,
    "total_pemasukan": 337957884,
    "total_pengeluaran": 625099,
    "rugi": 0,
    "profit": 337332785
  },
  {
    "waktu": "2025-07-08T14:05:11.362003",
    "modal_awal": 2102952,
    "total_pemasukan": 116562356,
    "total_pengeluaran": 347398,
    "rugi": 0,
    "profit": 116214958
  },
  {
    "waktu": "2025-07-08T14:06:11.362003",
    "modal_awal": 4521117,
    "total_pemasukan": 320307693,
    "total_pengeluaran": 844872,
    "rugi": 0,
    "profit": 319462821
  },
  {
    "waktu": "2025-07-08T14:07:11.362003",
    "modal_awal": 2890523,
    "total_pemasukan": 293559590,
    "total_pengeluaran": 469459,
    "rugi": 0,
    "profit": 293090131
  },
  {
    "waktu": "2025-07-08T14:08:11.362003",
    "modal_awal": 4079350,
    "total_pemasukan": 396873600,
    "total_pengeluaran": 533454,
    "rugi": 0,
    "profit": 396340146
  },
  {
    "waktu": "2025-07-08T14:09:11.362003",
    "modal_awal": 4463073,
    "total_pemasukan": 145679333,
    "total_pengeluaran": 971034,
    "rugi": 0,
    "profit": 144708299
  },
  {
    "waktu": "2025-07-08T14:10:11.362003",
    "modal_awal": 4850645,
    "total_pemasukan": 413293390,
    "total_pengeluaran": 868625,
    "rugi": 0,
    "profit": 412424765
  },
  {
    "waktu": "2025-07-08T14:11:11.362003",
    "modal_awal": 1882679,
    "total_pemasukan": 160300054,
    "total_pengeluaran": 603179,
    "rugi": 0,
    "profit": 159696875
  },
  {
    "waktu": "2025-07-08T14:12:11.362003",
    "modal_awal": 4121510,
    "total_pemasukan": 288032028,
    "total_pengeluaran": 181799,
    "rugi": 0,
    "profit": 287850229
  },
  {
    "waktu": "2025-07-08T14:13:11.362003",
    "modal_awal": 4115760,
    "total_pemasukan": 334627503,
    "total_pengeluaran": 464349,
    "rugi": 0,
    "profit": 334163154
  },
  {
    "waktu": "2025-07-08T14:14:11.362003",
    "modal_awal": 3790908,
    "total_pemasukan": 425400969,
    "total_pengeluaran": 931838,
    "rugi": 0,
    "profit": 424469131
  },
  {
    "waktu": "2025-07-08T14:15:11.362003",
    "modal_awal": 4256586,
    "total_pemasukan": 239866735,
    "total_pengeluaran": 723639,
    "rugi": 0,
    "profit": 239143096
  },
  {
    "waktu": "2025-07-08T14:16:11.362003",
    "modal_awal": 4306500,
    "total_pemasukan": 456030727,
    "total_pengeluaran": 893121,
    "rugi": 0,
    "profit": 455137606
  },
  {
    "waktu": "2025-07-08T14:17:11.362003",
    "modal_awal": 1767319,
    "total_pemasukan": 335258335,
    "total_pengeluaran": 770416,
    "rugi": 0,
    "profit": 334487919
  },
  {
    "waktu": "2025-07-08T14:18:11.362003",
    "modal_awal": 2273396,
    "total_pemasukan": 307991854,
    "total_pengeluaran": 990429,
    "rugi": 0,
    "profit": 307001425
  },
  {
    "waktu": "2025-07-08T14:19:11.362003",
    "modal_awal": 4911178,
    "total_pemasukan": 388670995,
    "total_pengeluaran": 155057,
    "rugi": 0,
    "profit": 388515938
  },
  {
    "waktu": "2025-07-08T14:20:11.362003",
    "modal_awal": 1123232,
    "total_pemasukan": 492344454,
    "total_pengeluaran": 755404,
    "rugi": 0,
    "profit": 491589050
  },
  {
    "waktu": "2025-07-08T14:21:11.362003",
    "modal_awal": 1148517,
    "total_pemasukan": 466265884,
    "total_pengeluaran": 667168,
    "rugi": 0,
    "profit": 465598716
  },
  {
    "waktu": "2025-07-08T14:22:11.362003",
    "modal_awal": 4469053,
    "total_pemasukan": 449287644,
    "total_pengeluaran": 648999,
    "rugi": 0,
    "profit": 448638645
  },
  {
    "waktu": "2025-07-08T14:23:11.362003",
    "modal_awal": 1745859,
    "total_pemasukan": 242229029,
    "total_pengeluaran": 717552,
    "rugi": 0,
    "profit": 241511477
  },
  {
    "waktu": "2025-07-08T14:24:11.362003",
    "modal_awal": 2823908,
    "total_pemasukan": 254608229,
    "total_pengeluaran": 616260,
    "rugi": 0,
    "profit": 253991969
  },
  {
    "waktu": "2025-07-08T14:25:11.362003",
    "modal_awal": 4415146,
    "total_pemasukan": 102416818,
    "total_pengeluaran": 117947,
    "rugi": 0,
    "profit": 102298871
  },
  {
    "waktu": "2025-07-08T14:26:11.362003",
    "modal_awal": 4738656,
    "total_pemasukan": 415177550,
    "total_pengeluaran": 585034,
    "rugi": 0,
    "profit": 414592516
  }
]